<?xml version="1.0" encoding="Windows-1252"?>
<GenericOperatorCollection xmlns:xsi="http://www.w3.org/2001/XMLSchema-instance" xmlns:xsd="http://www.w3.org/2001/XMLSchema">
  <GenericOperators>
    <GenericOperator Name="DataloaderOperator">
      <ID>2</ID>
      <Parent>-1</Parent>
      <PosX>-4</PosX>
      <PosY>2.5</PosY>
      <PosZ>3.494</PosZ>
    </GenericOperator>
    <GenericOperator Name="ScatterplotOperator">
      <ID>4</ID>
      <Parent>2</Parent>
      <PosX>-3</PosX>
      <PosY>2.5</PosY>
      <PosZ>3.494</PosZ>
    </GenericOperator>
    <GenericOperator Name="SplitOperator">
      <ID>6</ID>
      <Parent>4</Parent>
      <PosX>-2</PosX>
      <PosY>2.5</PosY>
      <PosZ>3.494</PosZ>
    </GenericOperator>
    <GenericOperator Name="ScatterplotOperator">
      <ID>7</ID>
      <Parent>6</Parent>
      <PosX>-1.01519227</PosX>
      <PosY>2.673648</PosY>
      <PosZ>3.494</PosZ>
    </GenericOperator>
    <GenericOperator Name="ScatterplotOperator">
      <ID>8</ID>
      <Parent>6</Parent>
      <PosX>-1.01519227</PosX>
      <PosY>2.326352</PosY>
      <PosZ>3.494</PosZ>
    </GenericOperator>
    <GenericOperator Name="DataloaderOperator">
      <ID>12</ID>
      <Parent>7</Parent>
      <PosX>-0.01519227</PosX>
      <PosY>2.673648</PosY>
      <PosZ>3.494</PosZ>
    </GenericOperator>
    <GenericOperator Name="DataloaderOperator">
      <ID>15</ID>
      <Parent>4</Parent>
      <PosX>-2</PosX>
      <PosY>3.1</PosY>
      <PosZ>3.494</PosZ>
    </GenericOperator>
    <GenericOperator Name="NewOperator">
      <ID>16</ID>
      <Parent>15</Parent>
      <PosX>-1</PosX>
      <PosY>3.1</PosY>
      <PosZ>3.494</PosZ>
    </GenericOperator>
  </GenericOperators>
</GenericOperatorCollection>